resend/__init__.py
resend/exceptions.py
resend/http_client.py
resend/http_client_requests.py
resend/pagination_helper.py
resend/py.typed
resend/request.py
resend/version.py
resend/api_keys/__init__.py
resend/api_keys/_api_key.py
resend/api_keys/_api_keys.py
resend/audiences/__init__.py
resend/audiences/_audience.py
resend/audiences/_audiences.py
resend/broadcasts/__init__.py
resend/broadcasts/_broadcast.py
resend/broadcasts/_broadcasts.py
resend/contacts/__init__.py
resend/contacts/_contact.py
resend/contacts/_contacts.py
resend/domains/__init__.py
resend/domains/_domain.py
resend/domains/_domains.py
resend/domains/_record.py
resend/emails/__init__.py
resend/emails/_attachment.py
resend/emails/_batch.py
resend/emails/_email.py
resend/emails/_emails.py
resend/emails/_tag.py
resend-2.17.0.dist-info/LICENSE.md
resend-2.17.0.dist-info/METADATA
resend-2.17.0.dist-info/WHEEL
resend-2.17.0.dist-info/top_level.txt
resend-2.17.0.dist-info/RECORD
