Metadata-Version: 2.1
Name: resend
Version: 2.17.0
Summary: Resend Python SDK
Home-page: https://github.com/resendlabs/resend-python
Author: Derich Pacheco
Author-email: carlosderich@gmail.com
Keywords: email,email platform
Classifier: Intended Audience :: Developers
Classifier: License :: OSI Approved :: MIT License
Classifier: Natural Language :: English
Classifier: Operating System :: OS Independent
Classifier: Programming Language :: Python :: 3.7
Classifier: Programming Language :: Python :: 3.8
Classifier: Programming Language :: Python :: 3.9
Classifier: Programming Language :: Python :: 3.10
Classifier: Programming Language :: Python :: 3.11
Requires-Python: >=3.7
License-File: LICENSE.md
Requires-Dist: requests>=2.31.0
Requires-Dist: typing_extensions>=4.4.0
